{
  "parent": "minecraft:recipes/root",
  "criteria": {
    "has_sky_steel_ingot": {
      "conditions": {
        "items": [
          {
            "items": "#c:ingots/sky_steel"
          }
        ]
      },
      "trigger": "minecraft:inventory_changed"
    },
    "has_the_recipe": {
      "conditions": {
        "recipe": "megacells:crafting/sky_steel_ingot_from_sky_steel_block"
      },
      "trigger": "minecraft:recipe_unlocked"
    }
  },
  "requirements": [
    [
      "has_the_recipe",
      "has_sky_steel_ingot"
    ]
  ],
  "rewards": {
    "recipes": [
      "megacells:crafting/sky_steel_ingot_from_sky_steel_block"
    ]
  }
}